risks/__init__.py
risks/filters.py
risks/filtersets.py
risks/forms.py
risks/graphql.py
risks/models.py
risks/navigation.py
risks/tables.py
risks/template_content.py
risks/urls.py
risks/views.py
risks/api/__init__.py
risks/api/serializers.py
risks/api/urls.py
risks/api/views.py
risks/migrations/0001_initial.py
risks/migrations/0002_alter_risk_custom_field_data_and_more.py
risks/migrations/0003_rename_content_type_riskassignment_object_type_and_more.py
risks/migrations/__init__.py
risks/templates/risks/risk.html
risks/templates/risks/risk_panel.html
risks/templates/risks/riskassignment_edit.html
risks/templates/risks/riskrelation.html
netbox_is_risks-0.2.1.dist-info/LICENSE
netbox_is_risks-0.2.1.dist-info/METADATA
netbox_is_risks-0.2.1.dist-info/WHEEL
netbox_is_risks-0.2.1.dist-info/top_level.txt
netbox_is_risks-0.2.1.dist-info/RECORD
